helpner/__init__.py
helpner/download.py
helpner/highlight.py
helpner/main.py
helpner/utils.py
helpner-0.0.1.dist-info/entry_points.txt
helpner-0.0.1.dist-info/LICENSE
helpner-0.0.1.dist-info/WHEEL
helpner-0.0.1.dist-info/METADATA
helpner-0.0.1.dist-info/RECORD
