Metadata-Version: 2.1
Name: helpner
Version: 0.0.1
Summary: Helpner, Named Entity Recognition applied to cli --help messages. 
Author-email: Agustín Piqueres <agustin.piqueres@gmail.com>
Classifier: Intended Audience :: Developers
Classifier: License :: OSI Approved :: GNU General Public License v3 or later (GPLv3+)
Classifier: Programming Language :: Python :: 3.10
Classifier: Programming Language :: Python :: 3.11
Requires-Dist: spacy>=3.5.0
Requires-Dist: rich>=12.6.0
Requires-Dist: black ; extra == "dev"
Requires-Dist: mypy ; extra == "dev"
Requires-Dist: ruff ; extra == "dev"
Requires-Dist: pytest>=7.2.0 ; extra == "test"
Requires-Dist: pytest-cov>=4.0.0 ; extra == "test"
Requires-Dist: pytest-mock>=3.10.0 ; extra == "test"
Requires-Dist: coverage>=7.1.0 ; extra == "test"
Requires-Dist: nox>=2022.11.21 ; extra == "test"
Project-URL: Source, https://github.com/plaguss/helpner
Provides-Extra: dev
Provides-Extra: test
